{
    "submaps":[
        {
            "num_points":113508,
            "file_name":"map_400_900.pcd",
            "center_x":450.0,
            "center_y":950.0
        },
        {
            "num_points":253068,
            "file_name":"map_400_800.pcd",
            "center_x":450.0,
            "center_y":850.0
        },
        {
            "num_points":24706,
            "file_name":"map_400_700.pcd",
            "center_x":450.0,
            "center_y":750.0
        },
        {
            "num_points":71601,
            "file_name":"map_400_600.pcd",
            "center_x":450.0,
            "center_y":650.0
        },
        {
            "num_points":11657,
            "file_name":"map_400_500.pcd",
            "center_x":450.0,
            "center_y":550.0
        },
        {
            "num_points":260,
            "file_name":"map_400_1800.pcd",
            "center_x":450.0,
            "center_y":1850.0
        },
        {
            "num_points":143237,
            "file_name":"map_400_1700.pcd",
            "center_x":450.0,
            "center_y":1750.0
        },
        {
            "num_points":445913,
            "file_name":"map_400_1600.pcd",
            "center_x":450.0,
            "center_y":1650.0
        },
        {
            "num_points":59596,
            "file_name":"map_400_1500.pcd",
            "center_x":450.0,
            "center_y":1550.0
        },
        {
            "num_points":164,
            "file_name":"map_400_1100.pcd",
            "center_x":450.0,
            "center_y":1150.0
        },
        {
            "num_points":52605,
            "file_name":"map_400_1000.pcd",
            "center_x":450.0,
            "center_y":1050.0
        },
        {
            "num_points":4118,
            "file_name":"map_300_900.pcd",
            "center_x":350.0,
            "center_y":950.0
        },
        {
            "num_points":139263,
            "file_name":"map_300_800.pcd",
            "center_x":350.0,
            "center_y":850.0
        },
        {
            "num_points":187637,
            "file_name":"map_300_700.pcd",
            "center_x":350.0,
            "center_y":750.0
        },
        {
            "num_points":247309,
            "file_name":"map_300_600.pcd",
            "center_x":350.0,
            "center_y":650.0
        },
        {
            "num_points":856,
            "file_name":"map_300_500.pcd",
            "center_x":350.0,
            "center_y":550.0
        },
        {
            "num_points":1537,
            "file_name":"map_300_1700.pcd",
            "center_x":350.0,
            "center_y":1750.0
        },
        {
            "num_points":31819,
            "file_name":"map_300_1600.pcd",
            "center_x":350.0,
            "center_y":1650.0
        },
        {
            "num_points":4291,
            "file_name":"map_300_1500.pcd",
            "center_x":350.0,
            "center_y":1550.0
        },
        {
            "num_points":40,
            "file_name":"map_2600_800.pcd",
            "center_x":2650.0,
            "center_y":850.0
        },
        {
            "num_points":18,
            "file_name":"map_2600_700.pcd",
            "center_x":2650.0,
            "center_y":750.0
        },
        {
            "num_points":2444,
            "file_name":"map_2500_900.pcd",
            "center_x":2550.0,
            "center_y":950.0
        },
        {
            "num_points":232831,
            "file_name":"map_2500_800.pcd",
            "center_x":2550.0,
            "center_y":850.0
        },
        {
            "num_points":55433,
            "file_name":"map_2500_700.pcd",
            "center_x":2550.0,
            "center_y":750.0
        },
        {
            "num_points":7031,
            "file_name":"map_2400_900.pcd",
            "center_x":2450.0,
            "center_y":950.0
        },
        {
            "num_points":265746,
            "file_name":"map_2400_800.pcd",
            "center_x":2450.0,
            "center_y":850.0
        },
        {
            "num_points":96759,
            "file_name":"map_2400_700.pcd",
            "center_x":2450.0,
            "center_y":750.0
        },
        {
            "num_points":2949,
            "file_name":"map_2300_900.pcd",
            "center_x":2350.0,
            "center_y":950.0
        },
        {
            "num_points":261586,
            "file_name":"map_2300_800.pcd",
            "center_x":2350.0,
            "center_y":850.0
        },
        {
            "num_points":112544,
            "file_name":"map_2300_700.pcd",
            "center_x":2350.0,
            "center_y":750.0
        },
        {
            "num_points":10330,
            "file_name":"map_2200_900.pcd",
            "center_x":2250.0,
            "center_y":950.0
        },
        {
            "num_points":500535,
            "file_name":"map_2200_800.pcd",
            "center_x":2250.0,
            "center_y":850.0
        },
        {
            "num_points":156286,
            "file_name":"map_2200_700.pcd",
            "center_x":2250.0,
            "center_y":750.0
        },
        {
            "num_points":413997,
            "file_name":"map_2100_900.pcd",
            "center_x":2150.0,
            "center_y":950.0
        },
        {
            "num_points":473177,
            "file_name":"map_2100_800.pcd",
            "center_x":2150.0,
            "center_y":850.0
        },
        {
            "num_points":189595,
            "file_name":"map_2100_700.pcd",
            "center_x":2150.0,
            "center_y":750.0
        },
        {
            "num_points":232,
            "file_name":"map_200_800.pcd",
            "center_x":250.0,
            "center_y":850.0
        },
        {
            "num_points":129,
            "file_name":"map_200_700.pcd",
            "center_x":250.0,
            "center_y":750.0
        },
        {
            "num_points":46028,
            "file_name":"map_200_600.pcd",
            "center_x":250.0,
            "center_y":650.0
        },
        {
            "num_points":185350,
            "file_name":"map_2000_900.pcd",
            "center_x":2050.0,
            "center_y":950.0
        },
        {
            "num_points":415668,
            "file_name":"map_2000_800.pcd",
            "center_x":2050.0,
            "center_y":850.0
        },
        {
            "num_points":458328,
            "file_name":"map_2000_700.pcd",
            "center_x":2050.0,
            "center_y":750.0
        },
        {
            "num_points":22794,
            "file_name":"map_2000_1000.pcd",
            "center_x":2050.0,
            "center_y":1050.0
        },
        {
            "num_points":35759,
            "file_name":"map_1900_900.pcd",
            "center_x":1950.0,
            "center_y":950.0
        },
        {
            "num_points":852665,
            "file_name":"map_1900_800.pcd",
            "center_x":1950.0,
            "center_y":850.0
        },
        {
            "num_points":522058,
            "file_name":"map_1900_700.pcd",
            "center_x":1950.0,
            "center_y":750.0
        },
        {
            "num_points":1299,
            "file_name":"map_1900_1100.pcd",
            "center_x":1950.0,
            "center_y":1150.0
        },
        {
            "num_points":206357,
            "file_name":"map_1900_1000.pcd",
            "center_x":1950.0,
            "center_y":1050.0
        },
        {
            "num_points":66598,
            "file_name":"map_1800_900.pcd",
            "center_x":1850.0,
            "center_y":950.0
        },
        {
            "num_points":508728,
            "file_name":"map_1800_800.pcd",
            "center_x":1850.0,
            "center_y":850.0
        },
        {
            "num_points":531391,
            "file_name":"map_1800_700.pcd",
            "center_x":1850.0,
            "center_y":750.0
        },
        {
            "num_points":8483,
            "file_name":"map_1800_1200.pcd",
            "center_x":1850.0,
            "center_y":1250.0
        },
        {
            "num_points":345147,
            "file_name":"map_1800_1100.pcd",
            "center_x":1850.0,
            "center_y":1150.0
        },
        {
            "num_points":163708,
            "file_name":"map_1800_1000.pcd",
            "center_x":1850.0,
            "center_y":1050.0
        },
        {
            "num_points":359763,
            "file_name":"map_1700_900.pcd",
            "center_x":1750.0,
            "center_y":950.0
        },
        {
            "num_points":1257210,
            "file_name":"map_1700_800.pcd",
            "center_x":1750.0,
            "center_y":850.0
        },
        {
            "num_points":327008,
            "file_name":"map_1700_700.pcd",
            "center_x":1750.0,
            "center_y":750.0
        },
        {
            "num_points":353,
            "file_name":"map_1700_1300.pcd",
            "center_x":1750.0,
            "center_y":1350.0
        },
        {
            "num_points":181910,
            "file_name":"map_1700_1200.pcd",
            "center_x":1750.0,
            "center_y":1250.0
        },
        {
            "num_points":203062,
            "file_name":"map_1700_1100.pcd",
            "center_x":1750.0,
            "center_y":1150.0
        },
        {
            "num_points":296612,
            "file_name":"map_1700_1000.pcd",
            "center_x":1750.0,
            "center_y":1050.0
        },
        {
            "num_points":318978,
            "file_name":"map_1600_900.pcd",
            "center_x":1650.0,
            "center_y":950.0
        },
        {
            "num_points":174082,
            "file_name":"map_1600_800.pcd",
            "center_x":1650.0,
            "center_y":850.0
        },
        {
            "num_points":25766,
            "file_name":"map_1600_700.pcd",
            "center_x":1650.0,
            "center_y":750.0
        },
        {
            "num_points":62748,
            "file_name":"map_1600_1300.pcd",
            "center_x":1650.0,
            "center_y":1350.0
        },
        {
            "num_points":221471,
            "file_name":"map_1600_1200.pcd",
            "center_x":1650.0,
            "center_y":1250.0
        },
        {
            "num_points":27672,
            "file_name":"map_1600_1100.pcd",
            "center_x":1650.0,
            "center_y":1150.0
        },
        {
            "num_points":5023,
            "file_name":"map_1600_1000.pcd",
            "center_x":1650.0,
            "center_y":1050.0
        },
        {
            "num_points":1779,
            "file_name":"map_1500_900.pcd",
            "center_x":1550.0,
            "center_y":950.0
        },
        {
            "num_points":271701,
            "file_name":"map_1500_800.pcd",
            "center_x":1550.0,
            "center_y":850.0
        },
        {
            "num_points":6197,
            "file_name":"map_1500_700.pcd",
            "center_x":1550.0,
            "center_y":750.0
        },
        {
            "num_points":344,
            "file_name":"map_1500_1400.pcd",
            "center_x":1550.0,
            "center_y":1450.0
        },
        {
            "num_points":202733,
            "file_name":"map_1500_1300.pcd",
            "center_x":1550.0,
            "center_y":1350.0
        },
        {
            "num_points":85207,
            "file_name":"map_1500_1200.pcd",
            "center_x":1550.0,
            "center_y":1250.0
        },
        {
            "num_points":28197,
            "file_name":"map_1500_1100.pcd",
            "center_x":1550.0,
            "center_y":1150.0
        },
        {
            "num_points":20,
            "file_name":"map_1500_1000.pcd",
            "center_x":1550.0,
            "center_y":1050.0
        },
        {
            "num_points":85137,
            "file_name":"map_1400_900.pcd",
            "center_x":1450.0,
            "center_y":950.0
        },
        {
            "num_points":48797,
            "file_name":"map_1400_800.pcd",
            "center_x":1450.0,
            "center_y":850.0
        },
        {
            "num_points":34,
            "file_name":"map_1400_1500.pcd",
            "center_x":1450.0,
            "center_y":1550.0
        },
        {
            "num_points":44564,
            "file_name":"map_1400_1400.pcd",
            "center_x":1450.0,
            "center_y":1450.0
        },
        {
            "num_points":96116,
            "file_name":"map_1400_1300.pcd",
            "center_x":1450.0,
            "center_y":1350.0
        },
        {
            "num_points":408758,
            "file_name":"map_1400_1200.pcd",
            "center_x":1450.0,
            "center_y":1250.0
        },
        {
            "num_points":10358,
            "file_name":"map_1400_1100.pcd",
            "center_x":1450.0,
            "center_y":1150.0
        },
        {
            "num_points":375,
            "file_name":"map_1400_1000.pcd",
            "center_x":1450.0,
            "center_y":1050.0
        },
        {
            "num_points":94614,
            "file_name":"map_1300_900.pcd",
            "center_x":1350.0,
            "center_y":950.0
        },
        {
            "num_points":185467,
            "file_name":"map_1300_800.pcd",
            "center_x":1350.0,
            "center_y":850.0
        },
        {
            "num_points":9397,
            "file_name":"map_1300_700.pcd",
            "center_x":1350.0,
            "center_y":750.0
        },
        {
            "num_points":11,
            "file_name":"map_1300_600.pcd",
            "center_x":1350.0,
            "center_y":650.0
        },
        {
            "num_points":1761,
            "file_name":"map_1300_1500.pcd",
            "center_x":1350.0,
            "center_y":1550.0
        },
        {
            "num_points":217293,
            "file_name":"map_1300_1400.pcd",
            "center_x":1350.0,
            "center_y":1450.0
        },
        {
            "num_points":61868,
            "file_name":"map_1300_1300.pcd",
            "center_x":1350.0,
            "center_y":1350.0
        },
        {
            "num_points":152033,
            "file_name":"map_1300_1200.pcd",
            "center_x":1350.0,
            "center_y":1250.0
        },
        {
            "num_points":105107,
            "file_name":"map_1300_1100.pcd",
            "center_x":1350.0,
            "center_y":1150.0
        },
        {
            "num_points":216060,
            "file_name":"map_1300_1000.pcd",
            "center_x":1350.0,
            "center_y":1050.0
        },
        {
            "num_points":221515,
            "file_name":"map_1200_900.pcd",
            "center_x":1250.0,
            "center_y":950.0
        },
        {
            "num_points":5441,
            "file_name":"map_1200_800.pcd",
            "center_x":1250.0,
            "center_y":850.0
        },
        {
            "num_points":77434,
            "file_name":"map_1200_700.pcd",
            "center_x":1250.0,
            "center_y":750.0
        },
        {
            "num_points":14106,
            "file_name":"map_1200_600.pcd",
            "center_x":1250.0,
            "center_y":650.0
        },
        {
            "num_points":21,
            "file_name":"map_1200_500.pcd",
            "center_x":1250.0,
            "center_y":550.0
        },
        {
            "num_points":68,
            "file_name":"map_1200_1600.pcd",
            "center_x":1250.0,
            "center_y":1650.0
        },
        {
            "num_points":78488,
            "file_name":"map_1200_1500.pcd",
            "center_x":1250.0,
            "center_y":1550.0
        },
        {
            "num_points":74623,
            "file_name":"map_1200_1400.pcd",
            "center_x":1250.0,
            "center_y":1450.0
        },
        {
            "num_points":113948,
            "file_name":"map_1200_1300.pcd",
            "center_x":1250.0,
            "center_y":1350.0
        },
        {
            "num_points":1806,
            "file_name":"map_1200_1200.pcd",
            "center_x":1250.0,
            "center_y":1250.0
        },
        {
            "num_points":27927,
            "file_name":"map_1200_1100.pcd",
            "center_x":1250.0,
            "center_y":1150.0
        },
        {
            "num_points":151507,
            "file_name":"map_1200_1000.pcd",
            "center_x":1250.0,
            "center_y":1050.0
        },
        {
            "num_points":62738,
            "file_name":"map_1100_900.pcd",
            "center_x":1150.0,
            "center_y":950.0
        },
        {
            "num_points":47942,
            "file_name":"map_1100_800.pcd",
            "center_x":1150.0,
            "center_y":850.0
        },
        {
            "num_points":1178,
            "file_name":"map_1100_700.pcd",
            "center_x":1150.0,
            "center_y":750.0
        },
        {
            "num_points":52837,
            "file_name":"map_1100_600.pcd",
            "center_x":1150.0,
            "center_y":650.0
        },
        {
            "num_points":14929,
            "file_name":"map_1100_500.pcd",
            "center_x":1150.0,
            "center_y":550.0
        },
        {
            "num_points":1451,
            "file_name":"map_1100_1500.pcd",
            "center_x":1150.0,
            "center_y":1550.0
        },
        {
            "num_points":32506,
            "file_name":"map_1100_1400.pcd",
            "center_x":1150.0,
            "center_y":1450.0
        },
        {
            "num_points":156238,
            "file_name":"map_1100_1300.pcd",
            "center_x":1150.0,
            "center_y":1350.0
        },
        {
            "num_points":3984,
            "file_name":"map_1100_1200.pcd",
            "center_x":1150.0,
            "center_y":1250.0
        },
        {
            "num_points":127637,
            "file_name":"map_1100_1100.pcd",
            "center_x":1150.0,
            "center_y":1150.0
        },
        {
            "num_points":4476,
            "file_name":"map_1100_1000.pcd",
            "center_x":1150.0,
            "center_y":1050.0
        },
        {
            "num_points":198,
            "file_name":"map_1000_900.pcd",
            "center_x":1050.0,
            "center_y":950.0
        },
        {
            "num_points":20209,
            "file_name":"map_1000_800.pcd",
            "center_x":1050.0,
            "center_y":850.0
        },
        {
            "num_points":59215,
            "file_name":"map_1000_700.pcd",
            "center_x":1050.0,
            "center_y":750.0
        },
        {
            "num_points":3012,
            "file_name":"map_1000_600.pcd",
            "center_x":1050.0,
            "center_y":650.0
        },
        {
            "num_points":78227,
            "file_name":"map_1000_500.pcd",
            "center_x":1050.0,
            "center_y":550.0
        },
        {
            "num_points":51717,
            "file_name":"map_1000_400.pcd",
            "center_x":1050.0,
            "center_y":450.0
        },
        {
            "num_points":150,
            "file_name":"map_1000_300.pcd",
            "center_x":1050.0,
            "center_y":350.0
        },
        {
            "num_points":4983,
            "file_name":"map_1000_1400.pcd",
            "center_x":1050.0,
            "center_y":1450.0
        },
        {
            "num_points":174283,
            "file_name":"map_1000_1300.pcd",
            "center_x":1050.0,
            "center_y":1350.0
        },
        {
            "num_points":186603,
            "file_name":"map_1000_1200.pcd",
            "center_x":1050.0,
            "center_y":1250.0
        },
        {
            "num_points":27456,
            "file_name":"map_1000_1100.pcd",
            "center_x":1050.0,
            "center_y":1150.0
        },
        {
            "num_points":201,
            "file_name":"map_900_800.pcd",
            "center_x":950.0,
            "center_y":850.0
        },
        {
            "num_points":9297,
            "file_name":"map_900_700.pcd",
            "center_x":950.0,
            "center_y":750.0
        },
        {
            "num_points":50147,
            "file_name":"map_900_600.pcd",
            "center_x":950.0,
            "center_y":650.0
        },
        {
            "num_points":736,
            "file_name":"map_900_500.pcd",
            "center_x":950.0,
            "center_y":550.0
        },
        {
            "num_points":84821,
            "file_name":"map_900_400.pcd",
            "center_x":950.0,
            "center_y":450.0
        },
        {
            "num_points":104433,
            "file_name":"map_900_300.pcd",
            "center_x":950.0,
            "center_y":350.0
        },
        {
            "num_points":9558,
            "file_name":"map_900_1400.pcd",
            "center_x":950.0,
            "center_y":1450.0
        },
        {
            "num_points":115255,
            "file_name":"map_900_1300.pcd",
            "center_x":950.0,
            "center_y":1350.0
        },
        {
            "num_points":49436,
            "file_name":"map_900_1200.pcd",
            "center_x":950.0,
            "center_y":1250.0
        },
        {
            "num_points":396,
            "file_name":"map_900_1100.pcd",
            "center_x":950.0,
            "center_y":1150.0
        },
        {
            "num_points":1733,
            "file_name":"map_800_600.pcd",
            "center_x":850.0,
            "center_y":650.0
        },
        {
            "num_points":110717,
            "file_name":"map_800_500.pcd",
            "center_x":850.0,
            "center_y":550.0
        },
        {
            "num_points":4756,
            "file_name":"map_800_400.pcd",
            "center_x":850.0,
            "center_y":450.0
        },
        {
            "num_points":150347,
            "file_name":"map_800_300.pcd",
            "center_x":850.0,
            "center_y":350.0
        },
        {
            "num_points":1224,
            "file_name":"map_800_1500.pcd",
            "center_x":850.0,
            "center_y":1550.0
        },
        {
            "num_points":142394,
            "file_name":"map_800_1400.pcd",
            "center_x":850.0,
            "center_y":1450.0
        },
        {
            "num_points":166892,
            "file_name":"map_800_1300.pcd",
            "center_x":850.0,
            "center_y":1350.0
        },
        {
            "num_points":15,
            "file_name":"map_800_1200.pcd",
            "center_x":850.0,
            "center_y":1250.0
        },
        {
            "num_points":16465,
            "file_name":"map_700_600.pcd",
            "center_x":750.0,
            "center_y":650.0
        },
        {
            "num_points":56627,
            "file_name":"map_700_500.pcd",
            "center_x":750.0,
            "center_y":550.0
        },
        {
            "num_points":137745,
            "file_name":"map_700_400.pcd",
            "center_x":750.0,
            "center_y":450.0
        },
        {
            "num_points":5127,
            "file_name":"map_700_300.pcd",
            "center_x":750.0,
            "center_y":350.0
        },
        {
            "num_points":108,
            "file_name":"map_700_1600.pcd",
            "center_x":750.0,
            "center_y":1650.0
        },
        {
            "num_points":199635,
            "file_name":"map_700_1500.pcd",
            "center_x":750.0,
            "center_y":1550.0
        },
        {
            "num_points":340962,
            "file_name":"map_700_1400.pcd",
            "center_x":750.0,
            "center_y":1450.0
        },
        {
            "num_points":86454,
            "file_name":"map_700_1300.pcd",
            "center_x":750.0,
            "center_y":1350.0
        },
        {
            "num_points":33,
            "file_name":"map_700_1200.pcd",
            "center_x":750.0,
            "center_y":1250.0
        },
        {
            "num_points":3994,
            "file_name":"map_600_700.pcd",
            "center_x":650.0,
            "center_y":750.0
        },
        {
            "num_points":47767,
            "file_name":"map_600_600.pcd",
            "center_x":650.0,
            "center_y":650.0
        },
        {
            "num_points":119791,
            "file_name":"map_600_500.pcd",
            "center_x":650.0,
            "center_y":550.0
        },
        {
            "num_points":22160,
            "file_name":"map_600_400.pcd",
            "center_x":650.0,
            "center_y":450.0
        },
        {
            "num_points":41,
            "file_name":"map_600_1700.pcd",
            "center_x":650.0,
            "center_y":1750.0
        },
        {
            "num_points":115179,
            "file_name":"map_600_1600.pcd",
            "center_x":650.0,
            "center_y":1650.0
        },
        {
            "num_points":86032,
            "file_name":"map_600_1500.pcd",
            "center_x":650.0,
            "center_y":1550.0
        },
        {
            "num_points":244123,
            "file_name":"map_600_1400.pcd",
            "center_x":650.0,
            "center_y":1450.0
        },
        {
            "num_points":212525,
            "file_name":"map_600_1300.pcd",
            "center_x":650.0,
            "center_y":1350.0
        },
        {
            "num_points":179493,
            "file_name":"map_600_1200.pcd",
            "center_x":650.0,
            "center_y":1250.0
        },
        {
            "num_points":4441,
            "file_name":"map_600_1100.pcd",
            "center_x":650.0,
            "center_y":1150.0
        },
        {
            "num_points":59,
            "file_name":"map_600_1000.pcd",
            "center_x":650.0,
            "center_y":1050.0
        },
        {
            "num_points":13,
            "file_name":"map_500_900.pcd",
            "center_x":550.0,
            "center_y":950.0
        },
        {
            "num_points":176,
            "file_name":"map_500_800.pcd",
            "center_x":550.0,
            "center_y":850.0
        },
        {
            "num_points":78366,
            "file_name":"map_500_700.pcd",
            "center_x":550.0,
            "center_y":750.0
        },
        {
            "num_points":65802,
            "file_name":"map_500_600.pcd",
            "center_x":550.0,
            "center_y":650.0
        },
        {
            "num_points":29195,
            "file_name":"map_500_500.pcd",
            "center_x":550.0,
            "center_y":550.0
        },
        {
            "num_points":27,
            "file_name":"map_500_400.pcd",
            "center_x":550.0,
            "center_y":450.0
        },
        {
            "num_points":14847,
            "file_name":"map_500_1700.pcd",
            "center_x":550.0,
            "center_y":1750.0
        },
        {
            "num_points":127344,
            "file_name":"map_500_1600.pcd",
            "center_x":550.0,
            "center_y":1650.0
        },
        {
            "num_points":208326,
            "file_name":"map_500_1500.pcd",
            "center_x":550.0,
            "center_y":1550.0
        },
        {
            "num_points":29437,
            "file_name":"map_500_1400.pcd",
            "center_x":550.0,
            "center_y":1450.0
        },
        {
            "num_points":378,
            "file_name":"map_500_1300.pcd",
            "center_x":550.0,
            "center_y":1350.0
        },
        {
            "num_points":20780,
            "file_name":"map_500_1200.pcd",
            "center_x":550.0,
            "center_y":1250.0
        },
        {
            "num_points":157614,
            "file_name":"map_500_1100.pcd",
            "center_x":550.0,
            "center_y":1150.0
        },
        {
            "num_points":111728,
            "file_name":"map_500_1000.pcd",
            "center_x":550.0,
            "center_y":1050.0
        }
    ],
    "num_submaps":181,
    "total_points":20344759
}